basic_iter/__init__.py
basic_iter/found.py
basic_iter/not_found.py
basic_iter/prim_list.py
basic_iter/type.py
basic_iter-0.0.4.dist-info/LICENSE
basic_iter-0.0.4.dist-info/WHEEL
basic_iter-0.0.4.dist-info/METADATA
basic_iter-0.0.4.dist-info/RECORD
