Metadata-Version: 2.1
Name: basic-iter
Version: 0.0.4
Summary: A basic set of functions on iterators
License: MIT
Author: Takayuki Goto
Author-email: nephits@gmail.com
Maintainer: Takayuki Goto
Maintainer-email: nephits@gmail.com
Requires-Python: >=3.7,<4.0
Classifier: License :: OSI Approved :: MIT License
Classifier: Operating System :: OS Independent
Classifier: Programming Language :: Python :: 3
Classifier: Programming Language :: Python :: 3.10
Classifier: Programming Language :: Python :: 3.7
Classifier: Programming Language :: Python :: 3.8
Classifier: Programming Language :: Python :: 3.9
Classifier: Topic :: Software Development :: Libraries
Classifier: Typing :: Typed
